MANIFEST.in
README.rst
requirements.txt
setup.cfg
setup.py
avalanche/__init__.py
avalanche/avl_app.py
avalanche/avl_hw.py
avalanche/avl_object.py
avalanche/avl_project.py
avalanche/avl_statistics_view.py
avalanche/api/__init__.py
avalanche/api/avl_tcl.py
avalanche/test/__init__.py
avalanche/test/sandbox.py
avalanche/test/test_base.py
avalanche/test/test_offline.py
avalanche/test/test_online.py
pyavalanche.egg-info/PKG-INFO
pyavalanche.egg-info/SOURCES.txt
pyavalanche.egg-info/dependency_links.txt
pyavalanche.egg-info/requires.txt
pyavalanche.egg-info/top_level.txt