Metadata-Version: 1.1
Name: pyavalanche
Version: 0.5.1
Summary: Python OO API package to automate Spirent Avalanche traffic generator
Home-page: https://github.com/shmir/PyAvalanche/
Author: Yoram Shamir
Author-email: yoram@ignissoft.com
License: Apache Software License
Platform: any
Classifier: Programming Language :: Python
Classifier: Development Status :: 4 - Beta
Classifier: Natural Language :: English
Classifier: Intended Audience :: Developers
Classifier: License :: OSI Approved :: Apache Software License
Classifier: Operating System :: OS Independent
Classifier: Topic :: Software Development :: Testing :: Traffic Generation
